charmarr_lib/krm/__init__.py
charmarr_lib/krm/_manager.py
charmarr_lib/krm/_models.py
charmarr_lib/krm/_version.py
charmarr_lib_krm-0.1.2.dist-info/METADATA
charmarr_lib_krm-0.1.2.dist-info/WHEEL
charmarr_lib_krm-0.1.2.dist-info/RECORD
