Metadata-Version: 2.4
Name: charmarr-lib-krm
Version: 0.1.2
Summary: Kubernetes Resource Manager with retry logic and reconciliation utilities
Author-email: Adhitya Ravi <adhityashan95@gmail.com>
License: LGPL-3.0-or-later
Classifier: Development Status :: 3 - Alpha
Classifier: Intended Audience :: Developers
Classifier: License :: OSI Approved :: GNU Lesser General Public License v3 or later (LGPLv3+)
Classifier: Programming Language :: Python :: 3
Classifier: Programming Language :: Python :: 3.12
Requires-Python: >=3.12
Requires-Dist: lightkube>=0.15
Requires-Dist: tenacity>=8.0
Provides-Extra: dev
Requires-Dist: mypy>=1.8; extra == 'dev'
Requires-Dist: pytest-cov>=4.0; extra == 'dev'
Requires-Dist: pytest>=8.0; extra == 'dev'
Requires-Dist: ruff>=0.1; extra == 'dev'
